{
"type": "FeatureCollection",
"name": "Point1",
"crs": { "type": "name", "properties": { "name": "urn:ogc:def:crs:OGC:1.3:CRS84" } },
"features": [
{ "type": "Feature", "properties": { "id": null, "Name": "Boston Logan Airport" }, "geometry": { "type": "Point", "coordinates": [ -71.01321024704022, 42.370848239897619 ] } }
]
}
